poly/Makefile
poly/__init__.py
poly/_poly.cpython-313-darwin.h
poly/_poly.cpython-313-darwin.so
poly/align.py
poly/alphabet.py
poly/build.py
poly/bwt.py
poly/checks.py
poly/clone.py
poly/codon.py
poly/fasta.py
poly/fastq.py
poly/fix.py
poly/fold.py
poly/fragment.py
poly/genbank.py
poly/gff.py
poly/go.py
poly/io.py
poly/mash.py
poly/matrix.py
poly/pcr.py
poly/pileup.py
poly/poly.c
poly/poly.go
poly/poly_go.h
poly/polyjson.py
poly/primers.py
poly/random.py
poly/rebase.py
poly/search.py
poly/seqhash.py
poly/slow5.py
poly/synthesis.py
poly/transform.py
poly/uniprot.py
poly/variants.py
clonai-0.0.1.dist-info/LICENSE
clonai-0.0.1.dist-info/METADATA
clonai-0.0.1.dist-info/WHEEL
clonai-0.0.1.dist-info/RECORD
