Metadata-Version: 2.1
Name: clonai
Version: 0.0.1
Summary: Python bindings for the DNA engineering library poly
License: MIT
Author: Timothy Stiles
Author-email: tim@stiles.io
Requires-Python: >=3.12,<4.0
Classifier: License :: OSI Approved :: MIT License
Classifier: Programming Language :: Python :: 3
Classifier: Programming Language :: Python :: 3.12
Classifier: Programming Language :: Python :: 3.13
